mimikko_util/__init__.py
mimikko_util/const_url.py
mimikko_util/error.py
mimikko_util/user/TokenUser.py
mimikko_util/user/User.py
mimikko_util/user/__init__.py
mimikko_util-1.2.dist-info/LICENSE
mimikko_util-1.2.dist-info/METADATA
mimikko_util-1.2.dist-info/WHEEL
mimikko_util-1.2.dist-info/top_level.txt
mimikko_util-1.2.dist-info/RECORD
