Metadata-Version: 2.1
Name: mimikko-util
Version: 1.2
Summary: 兽耳助手非官方模块，用于用户签到、能量值兑换、查询等操作
Home-page: https://gitee.com/MrDeveloper123/mimikko_util
Author: MrDeveloper123
Author-email: mrdeveloper123@outlook.com
License: Apache-2.0
Platform: all
Classifier: Development Status :: 4 - Beta
Classifier: License :: OSI Approved :: Apache Software License
Classifier: Natural Language :: Chinese (Simplified)
Classifier: Operating System :: OS Independent
Classifier: Programming Language :: Python :: Implementation
Classifier: Programming Language :: Python :: 3 :: Only
Classifier: Topic :: Software Development :: Libraries
Requires-Python: >=3
License-File: LICENSE
Requires-Dist: requests
